Metadata-Version: 1.0
Name: dredging
Version: 0.2.7
Summary: Collection of helper functions for dredging math
Home-page: https://github.com/Flawless/dredging
Author: Alexander Ushanov
Author-email: alushanov92@gmail.com
License: MIT
Platform: UNKNOWN
